pyutilix/__init__.py
pyutilix/utils.py
pyutilix-0.1.3.dist-info/METADATA
pyutilix-0.1.3.dist-info/WHEEL
pyutilix-0.1.3.dist-info/top_level.txt
pyutilix-0.1.3.dist-info/RECORD
