Metadata-Version: 2.4
Name: pyutilix
Version: 0.1.3
Summary: A small Python utility library including Clamped and other functions.
Author: M
License: MIT
Requires-Python: >=3.8
